sgtk/__init__.py
tank/__init__.py
tank/api.py
tank/constants.py
tank/context.py
tank/errors.py
tank/hook.py
tank/log.py
tank/path_cache.py
tank/pipelineconfig.py
tank/pipelineconfig_factory.py
tank/pipelineconfig_utils.py
tank/template.py
tank/template_includes.py
tank/template_path_parser.py
tank/templatekey.py
tank/authentication/__init__.py
tank/authentication/app_session_launcher.py
tank/authentication/console_authentication.py
tank/authentication/constants.py
tank/authentication/core_defaults_manager.py
tank/authentication/defaults_manager.py
tank/authentication/errors.py
tank/authentication/interactive_authentication.py
tank/authentication/invoker.py
tank/authentication/login_dialog.py
tank/authentication/session_cache.py
tank/authentication/shotgun_authenticator.py
tank/authentication/shotgun_wrapper.py
tank/authentication/site_info.py
tank/authentication/ui_authentication.py
tank/authentication/user.py
tank/authentication/user_impl.py
tank/authentication/utils.py
tank/authentication/web_login_support.py
tank/authentication/resources/backup_codes_light_bg.png
tank/authentication/resources/down-arrow.png
tank/authentication/resources/google_authenticator.png
tank/authentication/resources/login.graffle
tank/authentication/resources/login_dialog.ui
tank/authentication/resources/resources.qrc
tank/authentication/resources/shotgun_logo_light_medium.png
tank/authentication/sso_saml2/__init__.py
tank/authentication/sso_saml2/sso_saml2.py
tank/authentication/sso_saml2/sso_saml2_rv.py
tank/authentication/sso_saml2/sso_saml2_toolkit.py
tank/authentication/sso_saml2/utils.py
tank/authentication/sso_saml2/core/__init__.py
tank/authentication/sso_saml2/core/authentication_session_data.py
tank/authentication/sso_saml2/core/errors.py
tank/authentication/sso_saml2/core/sso_saml2_core.py
tank/authentication/sso_saml2/core/username_password_dialog.py
tank/authentication/sso_saml2/core/utils.py
tank/authentication/ui/__init__.py
sgtk-0.21.7.dist-info/LICENSE
sgtk-0.21.7.dist-info/METADATA
sgtk-0.21.7.dist-info/WHEEL
sgtk-0.21.7.dist-info/top_level.txt
sgtk-0.21.7.dist-info/RECORD
