Metadata-Version: 2.1
Name: sgtk
Version: 0.21.7
Summary: Flow Production Tracking Toolkit Core API
Home-page: https://github.com/shotgunsoftware/tk-core
Author: Autodesk, Inc
License: SHOTGUN PIPELINE TOOLKIT SOURCE CODE LICENSE
Platform: UNKNOWN
License-File: LICENSE
